LICENSE.md
MANIFEST.in
README.md
emtrees.h
emtreesmodule.cpp
requirements.dev.txt
requirements.txt
setup.py
emtrees/__init__.py
emtrees/randomforest.py
emtrees.egg-info/PKG-INFO
emtrees.egg-info/SOURCES.txt
emtrees.egg-info/dependency_links.txt
emtrees.egg-info/not-zip-safe
emtrees.egg-info/requires.txt
emtrees.egg-info/top_level.txt
examples/Performance comparison.ipynb
examples/digits.py
examples/sonar.py
test/test_emtrees.py