Metadata-Version: 2.1
Name: emtrees
Version: 0.2.5
Summary: Tree-based machine learning for embedded system
Home-page: https://github.com/jonnor/emtrees
Author: Jon Nordby
Author-email: jononor@gmail.com
License: UNKNOWN
Platform: UNKNOWN
